semicond/__init__.py
semicond/mplextension/NormalScale.py
semicond/mplextension/__init__.py
semicond/mplextension/normplot.py
semicond/mplextension/wafermap.py
semicond/stats/__init__.py
semicond/stats/estimator.py
semicond-0.1.0.dist-info/METADATA
semicond-0.1.0.dist-info/WHEEL
semicond-0.1.0.dist-info/top_level.txt
semicond-0.1.0.dist-info/RECORD
