Metadata-Version: 2.1
Name: semicond
Version: 0.1.0
Summary: Support functions for semiconductor field.
Author-email: Koen Van Sever <koen.vansever@gmail.com>
Requires-Dist: matplotlib (>=3.4)
Requires-Dist: pandas (>=1.5)
Requires-Dist: seaborn (>=0.12)
Provides-Extra: dev
Requires-Dist: twine ; extra == 'dev'
Requires-Dist: build ; extra == 'dev'
Provides-Extra: docs
Requires-Dist: sphinx ; extra == 'docs'
Requires-Dist: pydata-sphinx-theme ; extra == 'docs'
Provides-Extra: test
Requires-Dist: pytest ; extra == 'test'
